dgtest/__init__.py
dgtest/main.py
dgtest-1.0.2.dist-info/LICENSE.txt
dgtest-1.0.2.dist-info/METADATA
dgtest-1.0.2.dist-info/WHEEL
dgtest-1.0.2.dist-info/entry_points.txt
dgtest-1.0.2.dist-info/top_level.txt
dgtest-1.0.2.dist-info/RECORD
